d2d.py
desire2download.py
setup.py
Desire2Download.egg-info/PKG-INFO
Desire2Download.egg-info/SOURCES.txt
Desire2Download.egg-info/dependency_links.txt
Desire2Download.egg-info/entry_points.txt
Desire2Download.egg-info/requires.txt
Desire2Download.egg-info/top_level.txt